{
	"class" : {
		"categories" : "jb 7/24/2019 14:24",
		"categoryAnimating" : "jb 7/24/2019 13:47",
		"categoryBuildingAndTearingDown" : "jb 7/24/2019 13:48",
		"categoryDrawingAndStyling" : "TB 5/13/2021 15:12",
		"categoryEventHandling" : "jb 7/24/2019 13:49",
		"categoryFileHandling" : "jb 7/24/2019 14:25",
		"categoryLayouting" : "jb 7/24/2019 13:50",
		"categoryNestingAndSubmorphing" : "jb 7/24/2019 14:25",
		"categoryTransforming" : "jb 7/24/2019 14:25",
		"defaultButtonImageExtent" : "jb 7/24/2019 14:26",
		"labelAddition" : "jb 5/4/2019 13:37",
		"numberOfRows" : "FFN 5/21/2019 15:48" },
	"instance" : {
		"buildChildrenWith:" : "jb 7/24/2019 13:54",
		"categories" : "jb 5/1/2019 11:32",
		"categories:" : "jb 5/1/2019 11:33",
		"changeToExplorationViewFor:" : "KT 5/28/2021 14:48",
		"defaultMorphs" : "SH 5/17/2021 11:30",
		"defaultMorphs:" : "SH 5/27/2021 10:14",
		"initialize" : "SH 5/27/2021 11:36",
		"specFrameAt:for:" : "jb 7/24/2019 14:24",
		"specFrameFor:in:in:" : "jb 7/24/2019 14:01",
		"specSizePerRowFor:" : "lk 5/9/2019 20:38",
		"specsPerRowFor:" : "lk 5/9/2019 20:39" } }
